trajtrackerp/__init__.py
trajtrackerp/_res.py
trajtrackerp/common/_BaseConfig.py
trajtrackerp/common/_BaseExperimentInfo.py
trajtrackerp/common/_BaseTrialInfo.py
trajtrackerp/common/__init__.py
trajtrackerp/common/_common_funcs_init.py
trajtrackerp/common/_common_funcs_run.py
trajtrackerp/dchoice/_Config.py
trajtrackerp/dchoice/_ExperimentInfo.py
trajtrackerp/dchoice/_TrialInfo.py
trajtrackerp/dchoice/__init__.py
trajtrackerp/dchoice/_dc_init.py
trajtrackerp/dchoice/_dc_run.py
trajtrackerp/num2pos/_Config.py
trajtrackerp/num2pos/_DownArrow.py
trajtrackerp/num2pos/_ExperimentInfo.py
trajtrackerp/num2pos/_TrialInfo.py
trajtrackerp/num2pos/__init__.py
trajtrackerp/num2pos/_n2p_init.py
trajtrackerp/num2pos/_n2p_run.py
trajtrackerp-1.2.0.dist-info/DESCRIPTION.rst
trajtrackerp-1.2.0.dist-info/METADATA
trajtrackerp-1.2.0.dist-info/RECORD
trajtrackerp-1.2.0.dist-info/WHEEL
trajtrackerp-1.2.0.dist-info/metadata.json
trajtrackerp-1.2.0.dist-info/top_level.txt
trajtrackerp_res/images/confidence_slider_grey.bmp
trajtrackerp_res/images/confidence_slider_white.bmp
trajtrackerp_res/sounds/click.wav
trajtrackerp_res/sounds/error.wav
trajtrackerp_res/sounds/feedback-accuracy-0.wav
trajtrackerp_res/sounds/feedback-accuracy-1.wav
trajtrackerp_res/sounds/feedback-accuracy-2.wav
